excel_exporter/configuration/are_strings_grouped.py
excel_exporter/configuration/cell_format.py
excel_exporter/configuration/column.py
excel_exporter/configuration/excel_configuration.py
excel_exporter/configuration/group.py
excel_exporter/configuration/load_config.py
excel_exporter/configuration/sheet.py
excel_exporter/exporter/apply_sheet_configs.py
excel_exporter/exporter/character_validation.py
excel_exporter/exporter/create_excel.py
excel_exporter/exporter/write_columns_data.py
excel_exporter/exporter/write_columns_header.py
excel_exporter/exporter/write_groups_header.py
excel_exporter/exporter/write_sheet.py
excel_exporter/exporter/write_update_time.py
excel_exporter/utils/data_conversion.py
excel_exporter_bms-0.2.2.dist-info/METADATA
excel_exporter_bms-0.2.2.dist-info/entry_points.txt
excel_exporter_bms-0.2.2.dist-info/WHEEL
excel_exporter_bms-0.2.2.dist-info/LICENSE
excel_exporter_bms-0.2.2.dist-info/RECORD
