Metadata-Version: 2.1
Name: excel-exporter-bms
Version: 0.2.2
Summary: An excel exporter based on YAML configuration files
Home-page: https://github.com/brunomsantiago/excel_exporter
License: MIT
Author: Bruno Santiago
Author-email: not_a_real_email_13124123@gmail.com
Requires-Python: >=3.10,<4.0
Classifier: License :: OSI Approved :: MIT License
Classifier: Programming Language :: Python :: 3
Classifier: Programming Language :: Python :: 3.10
Classifier: Programming Language :: Python :: 3.11
Requires-Dist: PyYAML (>=6.0,<7.0)
Requires-Dist: openpyxl (>=3.1.1,<4.0.0)
